conveyor/__init__.py
conveyor/py.typed
conveyor/alerting/__init__.py
conveyor/factories/__init__.py
conveyor/operators/__init__.py
conveyor/secrets/__init__.py
conveyor/sensors/__init__.py
types_conveyor-0.0.9.dist-info/METADATA
types_conveyor-0.0.9.dist-info/WHEEL
types_conveyor-0.0.9.dist-info/top_level.txt
types_conveyor-0.0.9.dist-info/RECORD
