Metadata-Version: 2.4
Name: types-conveyor
Version: 0.0.9
Summary: Stubs for the Conveyor Airflow plugin
Author-email: Conveyor <support@conveyordata.com>
Project-URL: Homepage, https://conveyordata.com
Project-URL: Bug Tracker, https://github.com/datamindedbe/conveyor-roadmap/issues
Classifier: Development Status :: 4 - Beta
Classifier: Framework :: Apache Airflow
Classifier: Intended Audience :: Developers
Classifier: Operating System :: OS Independent
Classifier: Programming Language :: Python
Classifier: Programming Language :: Python :: 3
Classifier: Programming Language :: Python :: 3.8
Classifier: Programming Language :: Python :: 3.9
Classifier: Programming Language :: Python :: 3.10
Classifier: Programming Language :: Python :: 3.11
Requires-Python: >=3.8
